oca/__init__.py
oca/decorators/__init__.py
oca/decorators/foreach.py
oca/tests/__init__.py
oca/tests/common.py
oca/tests/test_helpers_foreach.py
oca_decorators-0.0.1.dist-info/DESCRIPTION.rst
oca_decorators-0.0.1.dist-info/METADATA
oca_decorators-0.0.1.dist-info/RECORD
oca_decorators-0.0.1.dist-info/WHEEL
oca_decorators-0.0.1.dist-info/metadata.json
oca_decorators-0.0.1.dist-info/top_level.txt
