Metadata-Version: 2.0
Name: oca-decorators
Version: 0.0.1
Summary: This is a library of decorators for Odoo developers.
Home-page: https://oca.github.io/oca-decorators
Author: Odoo Community Association (OCA)
Author-email: tools@odoo-community.org
License: LGPL-3
Download-URL: https://github.com/OCA/oca-decorators
Platform: UNKNOWN
Classifier: Development Status :: 4 - Beta
Classifier: Environment :: Console
Classifier: Framework :: Odoo
Classifier: Intended Audience :: Developers
Classifier: License :: OSI Approved :: GNU Lesser General Public License v3 or later (LGPLv3+)
Classifier: Programming Language :: Python
Classifier: Programming Language :: Python :: 2
Classifier: Programming Language :: Python :: 2.7
Classifier: Programming Language :: Python :: 3
Classifier: Programming Language :: Python :: 3.5
Classifier: Programming Language :: Python :: 3.6
Classifier: Topic :: Software Development :: Libraries :: Python Modules
Requires-Dist: decorator
